Phase_2/rtl/next_state_logic.v
`timescale 1ns/1ps

module next_state(
    //input
    input [4:0]current_state,
    input timer_done,
    input emergency_req_A,
    input emergency_req_B,
    input emergency_req_C,
    input emergency_req_D,
    input ped_req_A,
    input ped_req_B,
    input ped_req_C,
    input ped_req_D,
    //output
    output reg[4:0]next_state
);

//state encoding 

localparam S0  = 5'b00000;
localparam S1  = 5'b00001;
localparam S2  = 5'b00010;
localparam S3  = 5'b00011;
localparam S4  = 5'b00100;
localparam S5  = 5'b00101;
localparam S6  = 5'b00110;
localparam S7  = 5'b00111;
localparam S8  = 5'b01000;
localparam S9  = 5'b01001;
localparam S10 = 5'b01010;
localparam S11 = 5'b01011;
localparam S12 = 5'b01100;
localparam S13 = 5'b01101;
localparam S14 = 5'b01110;
localparam S15 = 5'b01111;
localparam S16 = 5'b10000;
localparam S17 = 5'b10001;
localparam S18 = 5'b10010;
localparam S19 = 5'b10011;

always @(*) begin
    case(current_state)
        S0 : begin
            if(emergency_req_A) begin
                next_state = S4;
            end 
            else if(emergency_req_B) begin
                next_state = S9;
            end 
            else if(emergency_req_C) begin
                next_state = S14;
            end 
            else if(emergency_req_D) begin
                next_state = S19;
            end 
            else if(timer_done == 1'b0) begin
                next_state = current_state;
            end 
            else begin
                next_state = S1;
            end 
        end 

        S1 : begin
            if(emergency_req_A) begin
                next_state = S4;
            end 
            else if(emergency_req_B) begin
                next_state = S9;
            end 
            else if(emergency_req_C) begin
                next_state = S14;
            end 
            else if(emergency_req_D) begin
                next_state = S19;
            end 
            else if(timer_done == 1'b0) begin
                next_state = current_state;
            end 
            else begin
                next_state = S2;
            end 
        end

        S2 : begin
            if(emergency_req_A) begin
                next_state = S4;
            end 
            else if(emergency_req_B) begin
                next_state = S9;
            end 
            else if(emergency_req_C) begin
                next_state = S14;
            end 
            else if(emergency_req_D) begin
                next_state = S19;
            end 
            else if(timer_done == 1'b0) begin
                next_state = current_state;
            end 
            else if(ped_req_A) begin
                next_state = S3;
            end 
            else begin
                next_state = S5;
            end 
        end

        S3 : begin
            if(emergency_req_A) begin
                next_state = S4;
            end 
            else if(emergency_req_B) begin
                next_state = S9;
            end 
            else if(emergency_req_C) begin
                next_state = S14;
            end 
            else if(emergency_req_D) begin
                next_state = S19;
            end 
            else if(timer_done == 1'b0) begin
                next_state = current_state;
            end 
            else begin
                next_state = S5;
            end 
        end

        S4 : begin
            if(emergency_req_A) begin
                next_state = current_state;
            end  
            else if(timer_done == 1'b0) begin
                next_state = current_state;
            end 
            else begin
                next_state = S0;
            end 
        end

        S5 : begin
            if(emergency_req_A) begin
                next_state = S4;
            end 
            else if(emergency_req_B) begin
                next_state = S9;
            end 
            else if(emergency_req_C) begin
                next_state = S14;
            end 
            else if(emergency_req_D) begin
                next_state = S19;
            end 
            else if(timer_done == 1'b0) begin
                next_state = current_state;
            end 
            else begin
                next_state = S6;
            end 
        end

        S6 : begin
            if(emergency_req_A) begin
                next_state = S4;
            end 
            else if(emergency_req_B) begin
                next_state = S9;
            end 
            else if(emergency_req_C) begin
                next_state = S14;
            end 
            else if(emergency_req_D) begin
                next_state = S19;
            end 
            else if(timer_done == 1'b0) begin
                next_state = current_state;
            end 
            else begin
                next_state = S7;
            end 
        end

        S7 : begin
            if(emergency_req_A) begin
                next_state = S4;
            end 
            else if(emergency_req_B) begin
                next_state = S9;
            end 
            else if(emergency_req_C) begin
                next_state = S14;
            end 
            else if(emergency_req_D) begin
                next_state = S19;
            end 
            else if(timer_done == 1'b0) begin
                next_state = current_state;
            end 
            else if(ped_req_B) begin
                next_state = S8;
            end 
            else begin
                next_state = S10;
            end 
        end

        S8 : begin
            if(emergency_req_A) begin
                next_state = S4;
            end 
            else if(emergency_req_B) begin
                next_state = S9;
            end 
            else if(emergency_req_C) begin
                next_state = S14;
            end 
            else if(emergency_req_D) begin
                next_state = S19;
            end 
            else if(timer_done == 1'b0) begin
                next_state = current_state;
            end 
            else begin
                next_state = S10;
            end 
        end

        S9 : begin
            if(emergency_req_B) begin
                next_state = current_state;
            end  
            else if(timer_done == 1'b0) begin
                next_state = current_state;
            end 
            else begin
                next_state = S0;
            end 
        end

        S10 : begin
            if(emergency_req_A) begin
                next_state = S4;
            end 
            else if(emergency_req_B) begin
                next_state = S9;
            end 
            else if(emergency_req_C) begin
                next_state = S14;
            end 
            else if(emergency_req_D) begin
                next_state = S19;
            end 
            else if(timer_done == 1'b0) begin
                next_state = current_state;
            end 
            else begin
                next_state = S11;
            end 
        end 

        S11 : begin
            if(emergency_req_A) begin
                next_state = S4;
            end 
            else if(emergency_req_B) begin
                next_state = S9;
            end 
            else if(emergency_req_C) begin
                next_state = S14;
            end 
            else if(emergency_req_D) begin
                next_state = S19;
            end 
            else if(timer_done == 1'b0) begin
                next_state = current_state;
            end 
            else begin
                next_state = S12;
            end 
        end

        S12 : begin
            if(emergency_req_A) begin
                next_state = S4;
            end 
            else if(emergency_req_B) begin
                next_state = S9;
            end 
            else if(emergency_req_C) begin
                next_state = S14;
            end 
            else if(emergency_req_D) begin
                next_state = S19;
            end 
            else if(timer_done == 1'b0) begin
                next_state = current_state;
            end 
            else if(ped_req_C) begin
                next_state = S13;
            end 
            else begin
                next_state = S15;
            end 
        end

        S13 : begin
            if(emergency_req_A) begin
                next_state = S4;
            end 
            else if(emergency_req_B) begin
                next_state = S9;
            end 
            else if(emergency_req_C) begin
                next_state = S14;
            end 
            else if(emergency_req_D) begin
                next_state = S19;
            end 
            else if(timer_done == 1'b0) begin
                next_state = current_state;
            end 
            else begin
                next_state = S15;
            end 
        end

        S14 : begin
            if(emergency_req_C) begin
                next_state = current_state;
            end  
            else if(timer_done == 1'b0) begin
                next_state = current_state;
            end 
            else begin
                next_state = S0;
            end 
        end

        S15 : begin
            if(emergency_req_A) begin
                next_state = S4;
            end 
            else if(emergency_req_B) begin
                next_state = S9;
            end 
            else if(emergency_req_C) begin
                next_state = S14;
            end 
            else if(emergency_req_D) begin
                next_state = S19;
            end 
            else if(timer_done == 1'b0) begin
                next_state = current_state;
            end 
            else begin
                next_state = S16;
            end 
        end 

        S16 : begin
            if(emergency_req_A) begin
                next_state = S4;
            end 
            else if(emergency_req_B) begin
                next_state = S9;
            end 
            else if(emergency_req_C) begin
                next_state = S14;
            end 
            else if(emergency_req_D) begin
                next_state = S19;
            end 
            else if(timer_done == 1'b0) begin
                next_state = current_state;
            end 
            else begin
                next_state = S17;
            end 
        end

        S17 : begin
            if(emergency_req_A) begin
                next_state = S4;
            end 
            else if(emergency_req_B) begin
                next_state = S9;
            end 
            else if(emergency_req_C) begin
                next_state = S14;
            end 
            else if(emergency_req_D) begin
                next_state = S19;
            end 
            else if(timer_done == 1'b0) begin
                next_state = current_state;
            end 
            else if(ped_req_D) begin
                next_state = S18;
            end 
            else begin
                next_state = S0;
            end 
        end

        S18 : begin
            if(emergency_req_A) begin
                next_state = S4;
            end 
            else if(emergency_req_B) begin
                next_state = S9;
            end 
            else if(emergency_req_C) begin
                next_state = S14;
            end 
            else if(emergency_req_D) begin
                next_state = S19;
            end 
            else if(timer_done == 1'b0) begin
                next_state = current_state;
            end 
            else begin
                next_state = S0;
            end 
        end

        S14 : begin
            if(emergency_req_D) begin
                next_state = current_state;
            end  
            else if(timer_done == 1'b0) begin
                next_state = current_state;
            end 
            else begin
                next_state = S0;
            end 
        end
    endcase 
end 
endmodule

Phase_2/tb/next_state_logic_TB.v
`timescale 1ns/1ps

module next_state_tb;

reg [4:0]current_state;
reg timer_done;
reg emergency_req_A;
reg emergency_req_B;
reg emergency_req_C;
reg emergency_req_D;
reg ped_req_A;
reg ped_req_B;
reg ped_req_C;
reg ped_req_D;

wire [4:0]next_state;

next_state dut(
    .current_state(current_state),
    .timer_done(timer_done),
    .emergency_req_A(emergency_req_A),
    .emergency_req_B(emergency_req_B),
    .emergency_req_C(emergency_req_C),
    .emergency_req_D(emergency_req_D),
    .ped_req_A(ped_req_A),
    .ped_req_B(ped_req_B),
    .ped_req_C(ped_req_C),
    .ped_req_D(ped_req_D),

    .next_state(next_state)
);

//state encoding 

localparam S0  = 5'b00000;
localparam S1  = 5'b00001;
localparam S2  = 5'b00010;
localparam S3  = 5'b00011;
localparam S4  = 5'b00100;
localparam S5  = 5'b00101;
localparam S6  = 5'b00110;
localparam S7  = 5'b00111;
localparam S8  = 5'b01000;
localparam S9  = 5'b01001;
localparam S10 = 5'b01010;
localparam S11 = 5'b01011;
localparam S12 = 5'b01100;
localparam S13 = 5'b01101;
localparam S14 = 5'b01110;
localparam S15 = 5'b01111;
localparam S16 = 5'b10000;
localparam S17 = 5'b10001;
localparam S18 = 5'b10010;
localparam S19 = 5'b10011;

initial begin
    $dumpfile("phase_2/wave/next_state.vcd");
    $dumpvars( 0 , next_state_tb);
end

initial begin

    //case 1 emergency request at S5 
    current_state = S5;
    timer_done = 1'b0;
    emergency_req_A = 1'b1;
    emergency_req_B = 1'b0;
    emergency_req_C = 1'b0;
    emergency_req_D = 1'b0;
    ped_req_A = 1'b0;
    ped_req_B = 1'b0;
    ped_req_C = 1'b0;
    ped_req_D = 1'b0;
    #10;

    //case check 
    if(next_state == S4)
        $display("case 1 : pass");
    else 
        $display("case 1 : failed");

    //case 2 emergency request at S1 
    current_state = S1;
    timer_done = 1'b0;
    emergency_req_A = 1'b0;
    emergency_req_B = 1'b1;
    emergency_req_C = 1'b0;
    emergency_req_D = 1'b0;
    ped_req_A = 1'b0;
    ped_req_B = 1'b0;
    ped_req_C = 1'b0;
    ped_req_D = 1'b0;
    #10;

    //case check 
    if(next_state == S9)
        $display("case 2 : pass");
    else 
        $display("case 2 : failed");

    //case 3 emergency request at S16 
    current_state = S16;
    timer_done = 1'b0;
    emergency_req_A = 1'b0;
    emergency_req_B = 1'b0;
    emergency_req_C = 1'b1;
    emergency_req_D = 1'b0;
    ped_req_A = 1'b0;
    ped_req_B = 1'b0;
    ped_req_C = 1'b0;
    ped_req_D = 1'b0;
    #10;

    //case check 
    if(next_state == S14)
        $display("case 3 : pass");
    else 
        $display("case 3 : failed");

    //case 4 timer_done = 1 then next state , current state is S1 then next state is S2 
    current_state = S6;
    timer_done = 1'b1;
    emergency_req_A = 1'b0;
    emergency_req_B = 1'b0;
    emergency_req_C = 1'b0;
    emergency_req_D = 1'b0;
    ped_req_A = 1'b1;
    ped_req_B = 1'b0;
    ped_req_C = 1'b0;
    ped_req_D = 1'b0;
    #10;

    //case check 
    if(next_state == S7)
        $display("case 4 : pass");
    else 
        $display("case 4 : failed");


    //case 5 ped_req_C = 1 then next state will be S13 
    current_state = S12;
    timer_done = 1'b1;
    emergency_req_A = 1'b0;
    emergency_req_B = 1'b0;
    emergency_req_C = 1'b0;
    emergency_req_D = 1'b0;
    ped_req_A = 1'b1;
    ped_req_B = 1'b0;
    ped_req_C = 1'b1;
    ped_req_D = 1'b0;
    #10;

    //case check 
    if(next_state == S13)
        $display("case 5 : pass");
    else 
        $display("case 5 : failed");

    //case 6 ped_req_D = 1 then next state will be S13 
    current_state = S17;
    timer_done = 1'b1;
    emergency_req_A = 1'b0;
    emergency_req_B = 1'b0;
    emergency_req_C = 1'b0;
    emergency_req_D = 1'b0;
    ped_req_A = 1'b1;
    ped_req_B = 1'b0;
    ped_req_C = 1'b1;
    ped_req_D = 1'b1;
    #10;

    //case check 
    if(next_state == S18)
        $display("case 6 : pass");
    else 
        $display("case 6 : failed");

    //case 7 ped_req_D = 0 then next state will be S0 
    current_state = S18;
    timer_done = 1'b1;
    emergency_req_A = 1'b0;
    emergency_req_B = 1'b0;
    emergency_req_C = 1'b0;
    emergency_req_D = 1'b0;
    ped_req_A = 1'b0;
    ped_req_B = 1'b0;
    ped_req_C = 1'b0;
    ped_req_D = 1'b0;
    #10;

    //case check 
    if(next_state == S0)
        $display("case 7 : pass");
    else 
        $display("case 7 : failed");

    //case 8 ped_req_B = 0 then next state will be S10
    current_state = S8;
    timer_done = 1'b1;
    emergency_req_A = 1'b0;
    emergency_req_B = 1'b0;
    emergency_req_C = 1'b0;
    emergency_req_D = 1'b0;
    ped_req_A = 1'b0;
    ped_req_B = 1'b0;
    ped_req_C = 1'b0;
    ped_req_D = 1'b0;
    #10;

    //case check 
    if(next_state == S10)
        $display("case 8 : pass");
    else 
        $display("case 8 : failed");

    //case 9 : check emergency state  
    current_state = S9;
    timer_done = 1'b1;
    emergency_req_A = 1'b0;
    emergency_req_B = 1'b0;
    emergency_req_C = 1'b0;
    emergency_req_D = 1'b0;
    ped_req_A = 1'b0;
    ped_req_B = 1'b0;
    ped_req_C = 1'b0;
    ped_req_D = 1'b0;
    #10;
    //case check 
    if(next_state == S0)
        $display("case 9 : pass");
    else 
        $display("case 9 : failed");

    //case 10 : check emergency state  
    current_state = S19;
    timer_done = 1'b1;
    emergency_req_A = 1'b0;
    emergency_req_B = 1'b0;
    emergency_req_C = 1'b0;
    emergency_req_D = 1'b0;
    ped_req_A = 1'b0;
    ped_req_B = 1'b0;
    ped_req_C = 1'b0;
    ped_req_D = 1'b0;
    #10;
    //case check 
    if(next_state == S0)
        $display("case 10 : pass");
    else 
        $display("case 10 : failed");

    //-----------------------------------

    //case 11 : current state is S6 and timer_done is 0 so the next state will be S6  
    current_state = S6;
    timer_done = 1'b0;
    emergency_req_A = 1'b0;
    emergency_req_B = 1'b0;
    emergency_req_C = 1'b0;
    emergency_req_D = 1'b0;
    ped_req_A = 1'b0;
    ped_req_B = 1'b0;
    ped_req_C = 1'b0;
    ped_req_D = 1'b0;
    #10;
    //case check 
    if(next_state == S6)
        $display("case 11 : pass");
    else 
        $display("case 11 : failed");
    
    //case 12 : current state is S4 emergency state emergency_req_A is 0 and timer_done is also 0  then the next state will be S4  
    current_state = S4;
    timer_done = 1'b0;
    emergency_req_A = 1'b0;
    emergency_req_B = 1'b0;
    emergency_req_C = 1'b0;
    emergency_req_D = 1'b0;
    ped_req_A = 1'b0;
    ped_req_B = 1'b0;
    ped_req_C = 1'b0;
    ped_req_D = 1'b0;
    #10;
    //case check 
    if(next_state == S4)
        $display("case 11 : pass");
    else 
        $display("case 11 : failed");

    $finish; 
end 
endmodule

Phase_2/wave/next_state.vcd
$date
	Wed Aug 19 14:21:11 2026
$end
$version
	Icarus Verilog
$end
$timescale
	1ps
$end
$scope module next_state_tb $end
$var wire 5 ! next_state [4:0] $end
$var parameter 5 " S0 $end
$var parameter 5 # S1 $end
$var parameter 5 $ S10 $end
$var parameter 5 % S11 $end
$var parameter 5 & S12 $end
$var parameter 5 ' S13 $end
$var parameter 5 ( S14 $end
$var parameter 5 ) S15 $end
$var parameter 5 * S16 $end
$var parameter 5 + S17 $end
$var parameter 5 , S18 $end
$var parameter 5 - S19 $end
$var parameter 5 . S2 $end
$var parameter 5 / S3 $end
$var parameter 5 0 S4 $end
$var parameter 5 1 S5 $end
$var parameter 5 2 S6 $end
$var parameter 5 3 S7 $end
$var parameter 5 4 S8 $end
$var parameter 5 5 S9 $end
$var reg 5 6 current_state [4:0] $end
$var reg 1 7 emergency_req_A $end
$var reg 1 8 emergency_req_B $end
$var reg 1 9 emergency_req_C $end
$var reg 1 : emergency_req_D $end
$var reg 1 ; ped_req_A $end
$var reg 1 < ped_req_B $end
$var reg 1 = ped_req_C $end
$var reg 1 > ped_req_D $end
$var reg 1 ? timer_done $end
$scope module dut $end
$var wire 5 @ current_state [4:0] $end
$var wire 1 7 emergency_req_A $end
$var wire 1 8 emergency_req_B $end
$var wire 1 9 emergency_req_C $end
$var wire 1 : emergency_req_D $end
$var wire 1 ; ped_req_A $end
$var wire 1 < ped_req_B $end
$var wire 1 = ped_req_C $end
$var wire 1 > ped_req_D $end
$var wire 1 ? timer_done $end
$var parameter 5 A S0 $end
$var parameter 5 B S1 $end
$var parameter 5 C S10 $end
$var parameter 5 D S11 $end
$var parameter 5 E S12 $end
$var parameter 5 F S13 $end
$var parameter 5 G S14 $end
$var parameter 5 H S15 $end
$var parameter 5 I S16 $end
$var parameter 5 J S17 $end
$var parameter 5 K S18 $end
$var parameter 5 L S19 $end
$var parameter 5 M S2 $end
$var parameter 5 N S3 $end
$var parameter 5 O S4 $end
$var parameter 5 P S5 $end
$var parameter 5 Q S6 $end
$var parameter 5 R S7 $end
$var parameter 5 S S8 $end
$var parameter 5 T S9 $end
$var reg 5 U next_state [4:0] $end
$upscope $end
$upscope $end
$enddefinitions $end
$comment Show the parameter values. $end
$dumpall
b1001 T
b1000 S
b111 R
b110 Q
b101 P
b100 O
b11 N
b10 M
b10011 L
b10010 K
b10001 J
b10000 I
b1111 H
b1110 G
b1101 F
b1100 E
b1011 D
b1010 C
b1 B
b0 A
b1001 5
b1000 4
b111 3
b110 2
b101 1
b100 0
b11 /
b10 .
b10011 -
b10010 ,
b10001 +
b10000 *
b1111 )
b1110 (
b1101 '
b1100 &
b1011 %
b1010 $
b1 #
b0 "
$end
#0
$dumpvars
b100 U
b101 @
0?
0>
0=
0<
0;
0:
09
08
17
b101 6
b100 !
$end
#10000
b1001 !
b1001 U
18
07
b1 6
b1 @
#20000
b1110 !
b1110 U
19
08
b10000 6
b10000 @
#30000
b111 !
b111 U
1;
09
1?
b110 6
b110 @
#40000
b1101 !
b1101 U
1=
b1100 6
b1100 @
#50000
b10010 !
b10010 U
1>
b10001 6
b10001 @
#60000
b0 !
b0 U
0>
0=
0;
b10010 6
b10010 @
#70000
b1010 !
b1010 U
b1000 6
b1000 @
#80000
b0 !
b0 U
b1001 6
b1001 @
#90000
b10011 6
b10011 @
#100000
b110 !
b110 U
0?
b110 6
b110 @
#110000
b100 !
b100 U
b100 6
b100 @
