Phase_2/rtl/state_register.v
`timescale 1ns/1ps 

module state_register(
    input clk,
    input reset,
    input [4:0]next_state,

    //output 
    output reg [4:0]current_state 
);

localparam S0  = 5'b00000;
localparam S1  = 5'b00001;
localparam S2  = 5'b00010;
localparam S3  = 5'b00011;
localparam S4  = 5'b00100;
localparam S5  = 5'b00101;
localparam S6  = 5'b00110;
localparam S7  = 5'b00111;
localparam S8  = 5'b01000;
localparam S9  = 5'b01001;
localparam S10 = 5'b01010;
localparam S11 = 5'b01011;
localparam S12 = 5'b01100;
localparam S13 = 5'b01101;
localparam S14 = 5'b01110;
localparam S15 = 5'b01111;
localparam S16 = 5'b10000;
localparam S17 = 5'b10001;
localparam S18 = 5'b10010;
localparam S19 = 5'b10011;
 

always @(posedge clk) begin
    if(reset) begin
        current_state <= S0;
    end
    else begin
        current_state <= next_state;
    end
end 
endmodule

Phase_2/tb/state_register_TB.v
`timescale 1ns/1ps 

module state_register_tb;

reg reset;
reg clk;
reg [4:0]next_state;
wire [4:0]current_state;

localparam S0  = 5'b00000;
localparam S1  = 5'b00001;
localparam S2  = 5'b00010;
localparam S3  = 5'b00011;
localparam S4  = 5'b00100;
localparam S5  = 5'b00101;
localparam S6  = 5'b00110;
localparam S7  = 5'b00111;
localparam S8  = 5'b01000;
localparam S9  = 5'b01001;
localparam S10 = 5'b01010;
localparam S11 = 5'b01011;
localparam S12 = 5'b01100;
localparam S13 = 5'b01101;
localparam S14 = 5'b01110;
localparam S15 = 5'b01111;
localparam S16 = 5'b10000;
localparam S17 = 5'b10001;
localparam S18 = 5'b10010;
localparam S19 = 5'b10011;

state_register dut(
    .clk(clk),
    .reset(reset),
    .next_state(next_state),
    .current_state(current_state)
);

initial begin
    clk = 1'b0;
end 
always #5 clk = ~clk;
initial begin
    $dumpfile("phase_2/wave/state_register.vcd");
    $dumpvars( 0 , state_register_tb);
end 

initial begin 
    @(posedge clk);
    //case 1 
    reset = 1'b1;
    next_state = S10;
    @(posedge clk);
    if(current_state == S0)
        $display("case 1 pass ");
    else 
        $display("case 1 failed");
    @(negedge clk);
    reset = 1'b0;
    #1;
    
    //case 2 
    @(posedge clk);
    next_state = S6;
    //@(posedge clk);
    #1;
    if (current_state == S6)
        $display("case 2 pass");
    else 
        $display("case 2 failed");

    // case 3 : check for hold 
    @(posedge clk);
    next_state = S15;
    #3;
    if(current_state == S15)
        $display("3A pass");
    else 
        $display("3A failed");
    
    next_state = S5;
    @(posedge clk);
    #1;
    if(current_state == S5)
        $display("3 pass");
    else 
        $display("3 failed");
    
    //case 4 
    @(posedge clk);
    next_state = S16;
    //@(posedge clk);
    #1;
    if (current_state == S16)
        $display("case 4 pass");
    else 
        $display("case 4 failed");
    repeat(3) @(posedge clk);
    $finish;
end 
endmodule

Phase_2/wave/state_register.vcd
$date
	Tue Aug 18 13:16:33 2026
$end
$version
	Icarus Verilog
$end
$timescale
	1ps
$end
$scope module state_register_tb $end
$var wire 5 ! current_state [4:0] $end
$var parameter 5 " S0 $end
$var parameter 5 # S1 $end
$var parameter 5 $ S10 $end
$var parameter 5 % S11 $end
$var parameter 5 & S12 $end
$var parameter 5 ' S13 $end
$var parameter 5 ( S14 $end
$var parameter 5 ) S15 $end
$var parameter 5 * S16 $end
$var parameter 5 + S17 $end
$var parameter 5 , S18 $end
$var parameter 5 - S19 $end
$var parameter 5 . S2 $end
$var parameter 5 / S3 $end
$var parameter 5 0 S4 $end
$var parameter 5 1 S5 $end
$var parameter 5 2 S6 $end
$var parameter 5 3 S7 $end
$var parameter 5 4 S8 $end
$var parameter 5 5 S9 $end
$var reg 1 6 clk $end
$var reg 5 7 next_state [4:0] $end
$var reg 1 8 reset $end
$scope module dut $end
$var wire 1 6 clk $end
$var wire 5 9 next_state [4:0] $end
$var wire 1 8 reset $end
$var parameter 5 : S0 $end
$var parameter 5 ; S1 $end
$var parameter 5 < S10 $end
$var parameter 5 = S11 $end
$var parameter 5 > S12 $end
$var parameter 5 ? S13 $end
$var parameter 5 @ S14 $end
$var parameter 5 A S15 $end
$var parameter 5 B S16 $end
$var parameter 5 C S17 $end
$var parameter 5 D S18 $end
$var parameter 5 E S19 $end
$var parameter 5 F S2 $end
$var parameter 5 G S3 $end
$var parameter 5 H S4 $end
$var parameter 5 I S5 $end
$var parameter 5 J S6 $end
$var parameter 5 K S7 $end
$var parameter 5 L S8 $end
$var parameter 5 M S9 $end
$var reg 5 N current_state [4:0] $end
$upscope $end
$upscope $end
$enddefinitions $end
$comment Show the parameter values. $end
$dumpall
b1001 M
b1000 L
b111 K
b110 J
b101 I
b100 H
b11 G
b10 F
b10011 E
b10010 D
b10001 C
b10000 B
b1111 A
b1110 @
b1101 ?
b1100 >
b1011 =
b1010 <
b1 ;
b0 :
b1001 5
b1000 4
b111 3
b110 2
b101 1
b100 0
b11 /
b10 .
b10011 -
b10010 ,
b10001 +
b10000 *
b1111 )
b1110 (
b1101 '
b1100 &
b1011 %
b1010 $
b1 #
b0 "
$end
#0
$dumpvars
bx N
bx 9
x8
bx 7
06
bx !
$end
#5000
b0 !
b0 N
b1010 7
b1010 9
18
16
#10000
06
#15000
16
#20000
08
06
#25000
b110 !
b110 N
b110 7
b110 9
16
#30000
06
#35000
b1111 !
b1111 N
b1111 7
b1111 9
16
#38000
b101 7
b101 9
#40000
06
#45000
b101 !
b101 N
16
#50000
06
#55000
b10000 !
b10000 N
b10000 7
b10000 9
16
