Phase_2/rtl/timer.v
`timescale 1ns/1ps 

module timer(
    //INPUT
    input clk,
    input reset,
    input timer_clear,
    input [4:0]target_count,
    
    //OUTPUT
    output timer_done
);
reg [4:0]count; 

always @(posedge clk) begin
    if (reset) begin
        count <= 5'd0;
    end 
    else if (timer_clear) begin
        count <= 5'd0;
    end 
    else if (count < target_count) begin
        count <= count + 5'd1; 
    end 
    //else begin
    //    count = target_count;
    //end 
end 
assign timer_done = (count >= target_count);
endmodule

Phase_2/tb/timer_TB.v
`timescale 1ns/1ps
module timer_TB ; 
reg clk;
reg reset;
reg timer_clear;
reg [4:0]target_count;

wire timer_done;

timer dut(
    //INPUT
    .clk(clk),
    .reset(reset),
    .timer_clear(timer_clear),
    .target_count(target_count),
    
    //OUTPUT
    .timer_done(timer_done)
);

initial begin
    clk = 1'b0;
end 

always #5 clk = ~ clk;
    initial begin
        $dumpfile("phase_2/wave/timer_wave.vcd");
        $dumpvars(0,timer_TB);
    end 

    initial begin
        // case 1
        @(posedge clk); 
        reset = 1'b1 ; timer_clear = 1'b0 ; target_count = 5'd30;
        @(posedge clk);
        reset = 1'b0;
        @(posedge clk);

        // case 2 
        reset = 1'b0 ; timer_clear = 1'b1 ; target_count = 5'd30;
        @(posedge clk);
        timer_clear = 1'b0;
        @(posedge clk);

        // case 3 
        reset = 1'b0 ; timer_clear = 1'b0 ; target_count = 5'd30;
        repeat(30) @(posedge clk);
        timer_clear = 1'b1;
        @(posedge clk);
        timer_clear = 1'b0;
        @(posedge clk);

        // case 4 
        reset = 1'b0 ; timer_clear = 1'b0 ; target_count = 5'd10;
        repeat(10) @(posedge clk);
        timer_clear = 1'b1;
        @(posedge clk);
        timer_clear = 1'b0;
        @(posedge clk);

        // case 5 
        reset = 1'b0; timer_clear = 1'b0; target_count = 5'd5; 
        repeat(10) @(posedge clk); // hold timer_done = 1 for next 5 positive clk edges
        timer_clear = 1'b1;
        @(posedge clk);
        timer_clear = 1'b0;
        @(posedge clk);

        $finish;
    end 
endmodule

Phase_2/wave/timer_wave.vcd
$date
	Tue Aug 18 13:11:48 2026
$end
$version
	Icarus Verilog
$end
$timescale
	1ps
$end
$scope module timer_TB $end
$var wire 1 ! timer_done $end
$var reg 1 " clk $end
$var reg 1 # reset $end
$var reg 5 $ target_count [4:0] $end
$var reg 1 % timer_clear $end
$scope module dut $end
$var wire 1 " clk $end
$var wire 1 # reset $end
$var wire 5 & target_count [4:0] $end
$var wire 1 % timer_clear $end
$var wire 1 ! timer_done $end
$var reg 5 ' count [4:0] $end
$upscope $end
$upscope $end
$enddefinitions $end
$comment Show the parameter values. $end
$dumpall
$end
#0
$dumpvars
bx '
bx &
x%
bx $
x#
0"
x!
$end
#5000
0!
b0 '
b11110 $
b11110 &
0%
1#
1"
#10000
0"
#15000
0#
1"
#20000
0"
#25000
1%
1"
#30000
0"
#35000
0%
1"
#40000
0"
#45000
b1 '
1"
#50000
0"
#55000
b10 '
1"
#60000
0"
#65000
b11 '
1"
#70000
0"
#75000
b100 '
1"
#80000
0"
#85000
b101 '
1"
#90000
0"
#95000
b110 '
1"
#100000
0"
#105000
b111 '
1"
#110000
0"
#115000
b1000 '
1"
#120000
0"
#125000
b1001 '
1"
#130000
0"
#135000
b1010 '
1"
#140000
0"
#145000
b1011 '
1"
#150000
0"
#155000
b1100 '
1"
#160000
0"
#165000
b1101 '
1"
#170000
0"
#175000
b1110 '
1"
#180000
0"
#185000
b1111 '
1"
#190000
0"
#195000
b10000 '
1"
#200000
0"
#205000
b10001 '
1"
#210000
0"
#215000
b10010 '
1"
#220000
0"
#225000
b10011 '
1"
#230000
0"
#235000
b10100 '
1"
#240000
0"
#245000
b10101 '
1"
#250000
0"
#255000
b10110 '
1"
#260000
0"
#265000
b10111 '
1"
#270000
0"
#275000
b11000 '
1"
#280000
0"
#285000
b11001 '
1"
#290000
0"
#295000
b11010 '
1"
#300000
0"
#305000
b11011 '
1"
#310000
0"
#315000
b11100 '
1"
#320000
0"
#325000
b11101 '
1"
#330000
0"
#335000
1!
b11110 '
1"
#340000
0"
#345000
0!
b0 '
1%
1"
#350000
0"
#355000
0%
1"
#360000
0"
#365000
b1 '
b1010 $
b1010 &
1"
#370000
0"
#375000
b10 '
1"
#380000
0"
#385000
b11 '
1"
#390000
0"
#395000
b100 '
1"
#400000
0"
#405000
b101 '
1"
#410000
0"
#415000
b110 '
1"
#420000
0"
#425000
b111 '
1"
#430000
0"
#435000
b1000 '
1"
#440000
0"
#445000
b1001 '
1"
#450000
0"
#455000
1!
b1010 '
1"
#460000
0"
#465000
0!
b0 '
1%
1"
#470000
0"
#475000
0%
1"
#480000
0"
#485000
b1 '
b101 $
b101 &
1"
#490000
0"
#495000
b10 '
1"
#500000
0"
#505000
b11 '
1"
#510000
0"
#515000
b100 '
1"
#520000
0"
#525000
1!
b101 '
1"
#530000
0"
#535000
1"
#540000
0"
#545000
1"
#550000
0"
#555000
1"
#560000
0"
#565000
1"
#570000
0"
#575000
1"
#580000
0"
#585000
0!
b0 '
1%
1"
#590000
0"
#595000
0%
1"
#600000
0"
#605000
b1 '
1"
