rtl/next_state_logic.v
`timescale 1ns/1ps

module next_state(
    //input
    input [3:0]current_state,
    input timer_done,
    input emergency_req_NS,
    input emergency_req_EW,
    input ped_req_NS,
    input ped_req_EW,
    //output
    output reg[3:0]next_state
);

//state encoding 

localparam S0 = 4'b0000; // NS_Green
localparam S1 = 4'b0001; // NS_yellow 
localparam S2 = 4'b0010; // All_red_NS
localparam S3 = 4'b0011; // walk_NS
localparam S4 = 4'b0100; //Emergency_NS
localparam S5 = 4'b0101; //EW_Green
localparam S6 = 4'b0110; //EW_yellow
localparam S7 = 4'b0111; //All_red_EW
localparam S8 = 4'b1000; //walk_EW
localparam S9 = 4'b1001; //Emergency_EW

always @(*) begin
    case(current_state)
        S0 : begin
            if(emergency_req_NS) begin
                next_state = S4;
            end 
            else if(emergency_req_EW) begin
                next_state = S9;
            end
            else if(timer_done == 1'b0) begin
                next_state = current_state;
            end 
            else begin
                next_state =  S1;
            end
        end

        S1 : begin
            if(emergency_req_NS) begin
                next_state = S4;
            end 
            else if(emergency_req_EW) begin
                next_state = S9;
            end
            else if(timer_done == 1'b0) begin
                next_state = current_state;
            end 
            else begin
                next_state =  S2;
            end
        end 

        S2 : begin
            if(emergency_req_NS) begin
                next_state = S4;
            end 
            else if(emergency_req_EW) begin
                next_state = S9;
            end
            else if(timer_done == 1'b0) begin
                next_state = current_state;
            end 
            else if(ped_req_NS) begin
                next_state =  S3;
            end
            else begin
                next_state = S5;
            end 
        end

        S3 : begin
            if(emergency_req_NS) begin
                next_state = S4;
            end 
            else if(emergency_req_EW) begin
                next_state = S9;
            end
            else if(timer_done == 1'b0) begin
                next_state = current_state;
            end 
            else begin
                next_state =  S5;
            end
        end

        S4 : begin
            if(emergency_req_NS) begin
                next_state = current_state;
            end 
            else if(timer_done == 1'b0) begin
                next_state = current_state;
            end 
            else begin
                next_state = S0;
            end 
        end 

        S5 : begin
            if(emergency_req_NS) begin
                next_state = S4;
            end 
            else if(emergency_req_EW) begin
                next_state = S9;
            end
            else if(timer_done == 1'b0) begin
                next_state = current_state;
            end 
            else begin
                next_state =  S6;
            end
        end

        S6 : begin
            if(emergency_req_NS) begin
                next_state = S4;
            end 
            else if(emergency_req_EW) begin
                next_state = S9;
            end
            else if(timer_done == 1'b0) begin
                next_state = current_state;
            end 
            else begin
                next_state =  S7;
            end
        end

        S7 : begin
            if(emergency_req_NS) begin
                next_state = S4;
            end 
            else if(emergency_req_EW) begin
                next_state = S9;
            end
            else if(timer_done == 1'b0) begin
                next_state = current_state;
            end 
            else if(ped_req_EW) begin
                next_state =  S8;
            end
            else begin
                next_state = S0;
            end 
        end 

        S8 : begin
            if(emergency_req_NS) begin
                next_state = S4;
            end 
            else if(emergency_req_EW) begin
                next_state = S9;
            end
            else if(timer_done == 1'b0) begin
                next_state = current_state;
            end
            else begin
                next_state = S0;
            end 
        end

        S9 : begin
            if(emergency_req_EW) begin
                next_state = S9;
            end
            else if(timer_done == 1'b0) begin
                next_state = current_state;
            end 
            else begin
                next_state = S0;
            end 
        end 

        default : begin
            next_state = S0;
        end 
    endcase 
end 
endmodule

tb/next_state_logic_TB.v
`timescale 1ns/1ps

module next_state_tb;

reg [3:0]current_state;
reg timer_done;
reg emergency_req_NS;
reg emergency_req_EW;
reg ped_req_NS;
reg ped_req_EW;

wire [3:0]next_state;

next_state dut(
    .current_state(current_state),
    .timer_done(timer_done),
    .emergency_req_NS(emergency_req_NS),
    .emergency_req_EW(emergency_req_EW),
    .ped_req_NS(ped_req_NS),
    .ped_req_EW(ped_req_EW),

    .next_state(next_state)
);

localparam S0 = 4'b0000; // NS_Green
localparam S1 = 4'b0001; // NS_yellow 
localparam S2 = 4'b0010; // All_red_NS
localparam S3 = 4'b0011; // walk_NS
localparam S4 = 4'b0100; //Emergency_NS
localparam S5 = 4'b0101; //EW_Green
localparam S6 = 4'b0110; //EW_yellow
localparam S7 = 4'b0111; //All_red_EW
localparam S8 = 4'b1000; //walk_EW
localparam S9 = 4'b1001; //Emergency_EW

initial begin
    $dumpfile("wave/next_state.vcd");
    $dumpvars( 0 , next_state_tb);

    //case 1 emergency request at S0 
    current_state = S0;
    timer_done = 1'b0;
    emergency_req_EW = 1'b1;
    emergency_req_NS = 1'b0;
    ped_req_NS = 1'b0;
    ped_req_EW = 1'b0;
    #10;
    //case check 
    if(next_state == S9)
        $display("case 1 : pass");
    else 
        $display("case 1 : failed");

    //case 2 emergency request at S0 
    current_state = S0;
    timer_done = 1'b0;
    emergency_req_EW = 1'b0;
    emergency_req_NS = 1'b1;
    ped_req_NS = 1'b0;
    ped_req_EW = 1'b0;
    #10;
    //case check 
    if(next_state ==  S4)
        $display("case 2 : pass");
    else 
        $display("case 2 : failed");

    //case 3 timer_done = 1 then next state , current state is S1 then next state is S2 
    current_state = S1;
    timer_done = 1'b1;
    emergency_req_EW = 1'b0;
    emergency_req_NS = 1'b0;
    ped_req_NS = 1'b1;
    ped_req_EW = 1'b0;
    #10;
    //case check 
    if(next_state == S2)
        $display("case 3 : pass");
    else 
        $display("case 3 : failed");

    //case 4 ped_req_NS = 1 then next state will be S3 
    current_state = S2;
    timer_done = 1'b1;
    emergency_req_EW = 1'b0;
    emergency_req_NS = 1'b0;
    ped_req_NS = 1'b1;
    ped_req_EW = 1'b0;
    #10;

    //case check 
    if(next_state == S3)
        $display("case 4 : pass");
    else 
        $display("case 4 : failed");

    //case 5 ped_req_EW = 0 then next state will be S0 
    current_state = S7;
    timer_done = 1'b1;
    emergency_req_EW = 1'b0;
    emergency_req_NS = 1'b0;
    ped_req_NS = 1'b0;
    ped_req_EW = 1'b0;
    #10;

    //case check 
    if(next_state == S0)
        $display("case 5 : pass");
    else 
        $display("case 5 : failed");

    //case 6 : check emergency state  
    current_state = S4;
    timer_done = 1'b1;
    emergency_req_EW = 1'b0;
    emergency_req_NS = 1'b0;
    ped_req_NS = 1'b0;
    ped_req_EW = 1'b0;
    #10;
    //case check 
    if(next_state == S0)
        $display("case 6 : pass");
    else 
        $display("case 6 : failed");

    //case 7 : current state is S6 and timer_done is 0 so the next state will be S6  
    current_state = S6;
    timer_done = 1'b0;
    emergency_req_EW = 1'b0;
    emergency_req_NS = 1'b0;
    ped_req_NS = 1'b0;
    ped_req_EW = 1'b0;
    #10;
    //case check 
    if(next_state == S6)
        $display("case 7 : pass");
    else 
        $display("case 7 : failed");
    
    //case 8 : current state is S9 emergency state emergency_req_EW is 0 and timer_done is also 0  then the next state will be S9  
    current_state = S9;
    timer_done = 1'b0;
    emergency_req_EW = 1'b0;
    emergency_req_NS = 1'b0;
    ped_req_NS = 1'b0;
    ped_req_EW = 1'b0;
    #10;
    //case check 
    if(next_state == S9)
        $display("case 8 : pass");
    else 
        $display("case 8 : failed");

    $finish; 
end 
endmodule

wave/next_state.vcd
$date
	Sun Aug 09 14:13:16 2026
$end
$version
	Icarus Verilog
$end
$timescale
	1ps
$end
$scope module next_state_tb $end
$var wire 4 ! next_state [3:0] $end
$var parameter 4 " S0 $end
$var parameter 4 # S1 $end
$var parameter 4 $ S2 $end
$var parameter 4 % S3 $end
$var parameter 4 & S4 $end
$var parameter 4 ' S5 $end
$var parameter 4 ( S6 $end
$var parameter 4 ) S7 $end
$var parameter 4 * S8 $end
$var parameter 4 + S9 $end
$var reg 4 , current_state [3:0] $end
$var reg 1 - emergency_req_EW $end
$var reg 1 . emergency_req_NS $end
$var reg 1 / ped_req_EW $end
$var reg 1 0 ped_req_NS $end
$var reg 1 1 timer_done $end
$scope module dut $end
$var wire 4 2 current_state [3:0] $end
$var wire 1 - emergency_req_EW $end
$var wire 1 . emergency_req_NS $end
$var wire 1 / ped_req_EW $end
$var wire 1 0 ped_req_NS $end
$var wire 1 1 timer_done $end
$var parameter 4 3 S0 $end
$var parameter 4 4 S1 $end
$var parameter 4 5 S2 $end
$var parameter 4 6 S3 $end
$var parameter 4 7 S4 $end
$var parameter 4 8 S5 $end
$var parameter 4 9 S6 $end
$var parameter 4 : S7 $end
$var parameter 4 ; S8 $end
$var parameter 4 < S9 $end
$var reg 4 = next_state [3:0] $end
$upscope $end
$upscope $end
$enddefinitions $end
$comment Show the parameter values. $end
$dumpall
b1001 <
b1000 ;
b111 :
b110 9
b101 8
b100 7
b11 6
b10 5
b1 4
b0 3
b1001 +
b1000 *
b111 )
b110 (
b101 '
b100 &
b11 %
b10 $
b1 #
b0 "
$end
#0
$dumpvars
b1001 =
b0 2
01
00
0/
0.
1-
b0 ,
b1001 !
$end
#10000
b100 !
b100 =
1.
0-
#20000
b10 !
b10 =
10
0.
11
b1 ,
b1 2
#30000
b11 !
b11 =
b10 ,
b10 2
#40000
b0 !
b0 =
00
b111 ,
b111 2
#50000
b100 ,
b100 2
#60000
b110 !
b110 =
01
b110 ,
b110 2
#70000
b1001 !
b1001 =
b1001 ,
b1001 2
