rtl/output_logic.v
`timescale 1ns/1ps 

module output_logic(
    //Input 
    input [3:0]current_state,
    //Output 
    output reg NS_Green,
    output reg NS_yellow,
    output reg NS_red,
    output reg EW_Green,
    output reg EW_yellow,
    output reg EW_red,
    output reg walk_NS,
    output reg dont_walk_NS,
    output reg walk_EW,
    output reg dont_walk_EW

);

//state encoding 

localparam S0 = 4'b0000; // NS_Green
localparam S1 = 4'b0001; // NS_yellow 
localparam S2 = 4'b0010; // All_red_NS
localparam S3 = 4'b0011; // walk_NS
localparam S4 = 4'b0100; //Emergency_NS
localparam S5 = 4'b0101; //EW_Green
localparam S6 = 4'b0110; //EW_yellow
localparam S7 = 4'b0111; //All_red_EW
localparam S8 = 4'b1000; //walk_EW
localparam S9 = 4'b1001; //Emergency_EW

always @(*) begin
    NS_Green = 1'b0;
    NS_yellow = 1'b0;
    NS_red = 1'b0;
    EW_Green = 1'b0;
    EW_yellow = 1'b0;
    EW_red = 1'b0;
    walk_NS = 1'b0;
    dont_walk_NS = 1'b0;
    walk_EW = 1'b0;
    dont_walk_EW = 1'b0;

    case(current_state)
        S0 : begin
            NS_Green = 1'b1;
            NS_yellow = 1'b0;
            NS_red = 1'b0;
            EW_Green = 1'b0;
            EW_yellow = 1'b0;
            EW_red = 1'b1;
            walk_NS = 1'b0;
            dont_walk_NS = 1'b1;
            walk_EW = 1'b0;
            dont_walk_EW = 1'b1;
        end

        S1 : begin
            NS_Green = 1'b0;
            NS_yellow = 1'b1;
            NS_red = 1'b0;
            EW_Green = 1'b0;
            EW_yellow = 1'b0;
            EW_red = 1'b1;
            walk_NS = 1'b0;
            dont_walk_NS = 1'b1;
            walk_EW = 1'b0;
            dont_walk_EW = 1'b1;
        end

        S2 : begin
            NS_Green = 1'b0;
            NS_yellow = 1'b0;
            NS_red = 1'b1;
            EW_Green = 1'b0;
            EW_yellow = 1'b0;
            EW_red = 1'b1;
            walk_NS = 1'b0;
            dont_walk_NS = 1'b1;
            walk_EW = 1'b0;
            dont_walk_EW = 1'b1;
        end

        S3 : begin
            NS_Green = 1'b0;
            NS_yellow = 1'b0;
            NS_red = 1'b1;
            EW_Green = 1'b0;
            EW_yellow = 1'b0;
            EW_red = 1'b1;
            walk_NS = 1'b1;
            dont_walk_NS = 1'b0;
            walk_EW = 1'b0;
            dont_walk_EW = 1'b1;
        end

        S4 : begin
            NS_Green = 1'b1;
            NS_yellow = 1'b0;
            NS_red = 1'b0;
            EW_Green = 1'b0;
            EW_yellow = 1'b0;
            EW_red = 1'b1;
            walk_NS = 1'b0;
            dont_walk_NS = 1'b1;
            walk_EW = 1'b0;
            dont_walk_EW = 1'b1;
        end

        S5 : begin
            NS_Green = 1'b0;
            NS_yellow = 1'b0;
            NS_red = 1'b1;
            EW_Green = 1'b1;
            EW_yellow = 1'b0;
            EW_red = 1'b0;
            walk_NS = 1'b0;
            dont_walk_NS = 1'b1;
            walk_EW = 1'b0;
            dont_walk_EW = 1'b1;
        end

        S6 : begin
            NS_Green = 1'b0;
            NS_yellow = 1'b0;
            NS_red = 1'b1;
            EW_Green = 1'b0;
            EW_yellow = 1'b1;
            EW_red = 1'b0;
            walk_NS = 1'b0;
            dont_walk_NS = 1'b1;
            walk_EW = 1'b0;
            dont_walk_EW = 1'b1;
        end

        S7 : begin
            NS_Green = 1'b0;
            NS_yellow = 1'b0;
            NS_red = 1'b1;
            EW_Green = 1'b0;
            EW_yellow = 1'b0;
            EW_red = 1'b1;
            walk_NS = 1'b0;
            dont_walk_NS = 1'b1;
            walk_EW = 1'b0;
            dont_walk_EW = 1'b1;
        end

        S8 : begin
            NS_Green = 1'b0;
            NS_yellow = 1'b0;
            NS_red = 1'b1;
            EW_Green = 1'b0;
            EW_yellow = 1'b0;
            EW_red = 1'b1;
            walk_NS = 1'b0;
            dont_walk_NS = 1'b1;
            walk_EW = 1'b1;
            dont_walk_EW = 1'b0;
        end

        S9 : begin
            NS_Green = 1'b0;
            NS_yellow = 1'b0;
            NS_red = 1'b1;
            EW_Green = 1'b1;
            EW_yellow = 1'b0;
            EW_red = 1'b0;
            walk_NS = 1'b0;
            dont_walk_NS = 1'b1;
            walk_EW = 1'b0;
            dont_walk_EW = 1'b1;
        end

        default : begin
            NS_Green = 1'b0;
            NS_yellow = 1'b0;
            NS_red = 1'b0;
            EW_Green = 1'b0;
            EW_yellow = 1'b0;
            EW_red = 1'b0;
            walk_NS = 1'b0;
            dont_walk_NS = 1'b0;
            walk_EW = 1'b0;
            dont_walk_EW = 1'b0;
        end 
    endcase
end 
endmodule

tb/output_logic_TB.v
`timescale 1ns/1ps 

module output_logic_tb ;

reg [3:0] current_state;
wire NS_Green;
wire NS_yellow;
wire NS_red;
wire EW_Green;
wire EW_yellow;
wire EW_red;
wire walk_NS;
wire dont_walk_NS;
wire walk_EW;
wire dont_walk_EW; 

localparam S0 = 4'b0000; // NS_Green
localparam S1 = 4'b0001; // NS_yellow 
localparam S2 = 4'b0010; // All_red_NS
localparam S3 = 4'b0011; // walk_NS
localparam S4 = 4'b0100; //Emergency_NS
localparam S5 = 4'b0101; //EW_Green
localparam S6 = 4'b0110; //EW_yellow
localparam S7 = 4'b0111; //All_red_EW
localparam S8 = 4'b1000; //walk_EW
localparam S9 = 4'b1001; //Emergency_EW

output_logic dut( 
    .current_state(current_state),
 
    .NS_Green(NS_Green),
    .NS_yellow(NS_yellow),
    .NS_red(NS_red),
    .EW_Green(EW_Green),
    .EW_yellow(EW_yellow),
    .EW_red(EW_red),
    .walk_NS(walk_NS),
    .dont_walk_NS(dont_walk_NS),
    .walk_EW(walk_EW),
    .dont_walk_EW(dont_walk_EW)
);

initial begin
    $dumpfile("wave/output_logic.vcd");
    $dumpvars( 0 , output_logic_tb);
    //Case 1 
    current_state = S0 ;
    #10;

    if (NS_Green == 1'b1 && NS_yellow == 1'b0 && NS_red == 1'b0 && EW_Green == 1'b0 && EW_yellow == 1'b0 && EW_red == 1'b1 && walk_NS == 1'b0 && dont_walk_NS == 1'b1 && walk_EW == 1'b0 && dont_walk_EW == 1'b1)
        $display ("case 1 :  Pass");
    else
        $display("Case 1 : failed"); 

    //case 2 
    current_state = S1;
    #10;

    if (NS_Green == 1'b0 &&
        NS_yellow == 1'b1 &&
        NS_red == 1'b0 &&
        EW_Green == 1'b0 &&
        EW_yellow == 1'b0 &&
        EW_red == 1'b1 &&
        walk_NS == 1'b0 && 
        dont_walk_NS == 1'b1 &&
        walk_EW == 1'b0  &&
        dont_walk_EW == 1'b1) begin
            $display ("case 2 :  Pass");
    end 
    else
        $display("Case 2 : failed");
     
     //case 3
     current_state = S2;
     #10;

    if(NS_Green == 1'b0 &&
        NS_yellow == 1'b0 &&
        NS_red == 1'b1 &&
        EW_Green == 1'b0 &&
        EW_yellow == 1'b0 &&
        EW_red == 1'b1 &&
        walk_NS == 1'b0 &&
        dont_walk_NS == 1'b1 &&
        walk_EW == 1'b0 &&
        dont_walk_EW == 1'b1)
            $display ("case 3 :  Pass");
    else
        $display("Case 3 : failed");
    
    //case 4 
    current_state = S3;
    #10;
    if(NS_Green == 1'b0 &&
        NS_yellow == 1'b0 &&
        NS_red == 1'b1 &&
        EW_Green == 1'b0 &&
        EW_yellow == 1'b0 &&
        EW_red == 1'b1 &&
        walk_NS == 1'b1 &&
        dont_walk_NS == 1'b0 &&
        walk_EW == 1'b0 &&
        dont_walk_EW == 1'b1)
            $display ("case 4 :  Pass");
    else
        $display("Case 4 : failed");
    
    //case 5
    current_state = S4 ;
    #10;

    if (NS_Green == 1'b1 && NS_yellow == 1'b0 && NS_red == 1'b0 && EW_Green == 1'b0 && EW_yellow == 1'b0 && EW_red == 1'b1 && walk_NS == 1'b0 && dont_walk_NS == 1'b1 && walk_EW == 1'b0 && dont_walk_EW == 1'b1)
        $display ("case 5 :  Pass");
    else
        $display("Case 5 : failed");
    
    //case 6 
    current_state = S5;
    #10;
    if(NS_Green == 1'b0 &&
        NS_yellow == 1'b0 &&
        NS_red == 1'b1 &&
        EW_Green == 1'b1 &&
        EW_yellow == 1'b0 &&
        EW_red == 1'b0 &&
        walk_NS == 1'b0 &&
        dont_walk_NS == 1'b1 &&
        walk_EW == 1'b0 &&
        dont_walk_EW == 1'b1)
            $display ("case 6 :  Pass");
    else
        $display("Case 6 : failed");

    //case 7 
    current_state = S6;
    #10;
    if(NS_Green == 1'b0 &&
        NS_yellow == 1'b0 &&
        NS_red == 1'b1 &&
        EW_Green == 1'b0 &&
        EW_yellow == 1'b1 &&
        EW_red == 1'b0 &&
        walk_NS == 1'b0 &&
        dont_walk_NS == 1'b1 &&
        walk_EW == 1'b0 &&
        dont_walk_EW == 1'b1)
            $display ("case 7 :  Pass");
    else
        $display("Case 7 : failed");
    
    //case 8
     current_state = S7;
     #10;

    if(NS_Green == 1'b0 &&
        NS_yellow == 1'b0 &&
        NS_red == 1'b1 &&
        EW_Green == 1'b0 &&
        EW_yellow == 1'b0 &&
        EW_red == 1'b1 &&
        walk_NS == 1'b0 &&
        dont_walk_NS == 1'b1 &&
        walk_EW == 1'b0 &&
        dont_walk_EW == 1'b1)
            $display ("case 8 :  Pass");
    else
        $display("Case 8 : failed");
    
    //case 9
     current_state = S8;
     #10;

    if (NS_Green == 1'b0 &&
        NS_yellow == 1'b0 &&
        NS_red == 1'b1 &&
        EW_Green == 1'b0 &&
        EW_yellow == 1'b0 &&
        EW_red == 1'b1 &&
        walk_NS == 1'b0 &&
        dont_walk_NS == 1'b1 &&
        walk_EW == 1'b1 &&
        dont_walk_EW == 1'b0)
            $display ("case 9 :  Pass");
    else
        $display("Case 9 : failed");

    //case 10
    current_state = S9;
    #10;
    if(NS_Green == 1'b0 &&
        NS_yellow == 1'b0 &&
        NS_red == 1'b1 &&
        EW_Green == 1'b1 &&
        EW_yellow == 1'b0 &&
        EW_red == 1'b0 &&
        walk_NS == 1'b0 &&
        dont_walk_NS == 1'b1 &&
        walk_EW == 1'b0 &&
        dont_walk_EW == 1'b1)
            $display ("case 10 :  Pass");
    else
        $display("Case 10 : failed");
        
end 
endmodule

wave/output_logic.vcd
$date
	Mon Aug 10 15:57:16 2026
$end
$version
	Icarus Verilog
$end
$timescale
	1ps
$end
$scope module output_logic_tb $end
$var wire 1 ! walk_NS $end
$var wire 1 " walk_EW $end
$var wire 1 # dont_walk_NS $end
$var wire 1 $ dont_walk_EW $end
$var wire 1 % NS_yellow $end
$var wire 1 & NS_red $end
$var wire 1 ' NS_Green $end
$var wire 1 ( EW_yellow $end
$var wire 1 ) EW_red $end
$var wire 1 * EW_Green $end
$var parameter 4 + S0 $end
$var parameter 4 , S1 $end
$var parameter 4 - S2 $end
$var parameter 4 . S3 $end
$var parameter 4 / S4 $end
$var parameter 4 0 S5 $end
$var parameter 4 1 S6 $end
$var parameter 4 2 S7 $end
$var parameter 4 3 S8 $end
$var parameter 4 4 S9 $end
$var reg 4 5 current_state [3:0] $end
$scope module dut $end
$var wire 4 6 current_state [3:0] $end
$var parameter 4 7 S0 $end
$var parameter 4 8 S1 $end
$var parameter 4 9 S2 $end
$var parameter 4 : S3 $end
$var parameter 4 ; S4 $end
$var parameter 4 < S5 $end
$var parameter 4 = S6 $end
$var parameter 4 > S7 $end
$var parameter 4 ? S8 $end
$var parameter 4 @ S9 $end
$var reg 1 * EW_Green $end
$var reg 1 ) EW_red $end
$var reg 1 ( EW_yellow $end
$var reg 1 ' NS_Green $end
$var reg 1 & NS_red $end
$var reg 1 % NS_yellow $end
$var reg 1 $ dont_walk_EW $end
$var reg 1 # dont_walk_NS $end
$var reg 1 " walk_EW $end
$var reg 1 ! walk_NS $end
$upscope $end
$upscope $end
$enddefinitions $end
$comment Show the parameter values. $end
$dumpall
b1001 @
b1000 ?
b111 >
b110 =
b101 <
b100 ;
b11 :
b10 9
b1 8
b0 7
b1001 4
b1000 3
b111 2
b110 1
b101 0
b100 /
b11 .
b10 -
b1 ,
b0 +
$end
#0
$dumpvars
b0 6
b0 5
0*
1)
0(
1'
0&
0%
1$
1#
0"
0!
$end
#10000
1%
1$
1#
1)
0'
b1 5
b1 6
#20000
1&
1$
1#
1)
0%
b10 5
b10 6
#30000
1!
1$
0#
1)
1&
b11 5
b11 6
#40000
1#
1'
1$
0!
1)
0&
b100 5
b100 6
#50000
1*
1&
1$
1#
0)
0'
b101 5
b101 6
#60000
1(
1$
1#
0*
1&
b110 5
b110 6
#70000
1)
1$
1#
0(
1&
b111 5
b111 6
#80000
1"
0$
1#
1)
1&
b1000 5
b1000 6
#90000
1$
1*
0"
1#
0)
1&
b1001 5
b1001 6
