rtl/state_register.v
`timescale 1ns/1ps 

module state_register(
    input clk,
    input reset,
    input [3:0]next_state,

    //output 
    output reg [3:0]current_state 
);

localparam S0 = 4'b0000;
localparam S1 = 4'b0001;
localparam S2 = 4'b0010;
localparam S3 = 4'b0011;
localparam S4 = 4'b0100;
localparam S5 = 4'b0101;
localparam S6 = 4'b0110;
localparam S7 = 4'b0111;
localparam S8 = 4'b1000;
localparam S9 = 4'b1001;

always @(posedge clk) begin
    if(reset) begin
        current_state <= S0;
    end
    else begin
        current_state <= next_state;
    end
end 
endmodule

tb/state_register_TB.v
`timescale 1ns/1ps 

module state_register_tb;

reg reset;
reg clk;
reg [3:0]next_state;
wire [3:0]current_state;

localparam S0 = 4'b0000;
localparam S1 = 4'b0001;
localparam S2 = 4'b0010;
localparam S3 = 4'b0011;
localparam S4 = 4'b0100;
localparam S5 = 4'b0101;
localparam S6 = 4'b0110;
localparam S7 = 4'b0111;
localparam S8 = 4'b1000;
localparam S9 = 4'b1001;

state_register dut(
    .clk(clk),
    .reset(reset),
    .next_state(next_state),
    .current_state(current_state)
);

initial begin
    clk = 1'b0;
end 
always #5 clk = ~clk;
initial begin
    $dumpfile("wave/state_register.vcd");
    $dumpvars( 0 , state_register_tb);
end 

initial begin 
    @(posedge clk);
    //case 1 
    reset = 1'b1 ; next_state = S7;
    @(posedge clk);
    if (current_state == S0)
        $display("case 1 Pass");
    else
        $display("case 1 fail");

    reset = 1'b0;
    @(posedge clk);

    //case 2
    next_state = S2;
    @(posedge clk);
    #1;
    if (current_state == S2)
        $display("case 2 Pass");
    else
        $display("case 2 fail");

    //case 3 
    next_state = S3;
    @(posedge clk);
    #1;
    if (current_state == S3)
        $display("case 3 Pass");
    else
        $display("case 3 fail");

    //case 4 state change between the +ve edge of clock 
    next_state = S6;
    #3;

    if (current_state == S3)
        $display("case 4A Pass");
    else
        $display("case 4A Fail");

    @(posedge clk);
    #1;
    if (current_state == S6)
        $display("case 4 Pass");
    else
        $display("case 4 Fail");

    $finish;

end 
endmodule

wave/state_register.vcd
$date
	Sat Aug 08 14:56:33 2026
$end
$version
	Icarus Verilog
$end
$timescale
	1ps
$end
$scope module state_register_tb $end
$var wire 4 ! current_state [3:0] $end
$var parameter 4 " S0 $end
$var parameter 4 # S1 $end
$var parameter 4 $ S2 $end
$var parameter 4 % S3 $end
$var parameter 4 & S4 $end
$var parameter 4 ' S5 $end
$var parameter 4 ( S6 $end
$var parameter 4 ) S7 $end
$var parameter 4 * S8 $end
$var parameter 4 + S9 $end
$var reg 1 , clk $end
$var reg 4 - next_state [3:0] $end
$var reg 1 . reset $end
$scope module dut $end
$var wire 1 , clk $end
$var wire 4 / next_state [3:0] $end
$var wire 1 . reset $end
$var parameter 4 0 S0 $end
$var parameter 4 1 S1 $end
$var parameter 4 2 S2 $end
$var parameter 4 3 S3 $end
$var parameter 4 4 S4 $end
$var parameter 4 5 S5 $end
$var parameter 4 6 S6 $end
$var parameter 4 7 S7 $end
$var parameter 4 8 S8 $end
$var parameter 4 9 S9 $end
$var reg 4 : current_state [3:0] $end
$upscope $end
$upscope $end
$enddefinitions $end
$comment Show the parameter values. $end
$dumpall
b1001 9
b1000 8
b111 7
b110 6
b101 5
b100 4
b11 3
b10 2
b1 1
b0 0
b1001 +
b1000 *
b111 )
b110 (
b101 '
b100 &
b11 %
b10 $
b1 #
b0 "
$end
#0
$dumpvars
bx :
bx /
x.
bx -
0,
bx !
$end
#5000
b0 !
b0 :
b111 -
b111 /
1.
1,
#10000
0,
#15000
0.
1,
#20000
0,
#25000
b10 !
b10 :
b10 -
b10 /
1,
#30000
0,
#35000
1,
#36000
b11 -
b11 /
#40000
0,
#45000
b11 !
b11 :
1,
#46000
b110 -
b110 /
#50000
0,
#55000
b110 !
b110 :
1,
