rtl/output_logic.v
`timescale 1ns/1ps 

module output_logic(
    //Input 
    input [3:0]current_state,
    //Output 
    output reg NS_Green,
    output reg NS_yellow,
    output reg NS_red,
    output reg EW_Green,
    output reg EW_yellow,
    output reg EW_red,
    output reg walk_NS,
    output reg dont_walk_NS,
    output reg walk_EW,
    output reg dont_walk_EW

);

//state encoding 

localparam S0 = 4'b0000; // NS_Green
localparam S1 = 4'b0001; // NS_yellow 
localparam S2 = 4'b0010; // All_red_NS
localparam S3 = 4'b0011; // walk_NS
localparam S4 = 4'b0100; //Emergency_NS
localparam S5 = 4'b0101; //EW_Green
localparam S6 = 4'b0110; //EW_yellow
localparam S7 = 4'b0111; //All_red_EW
localparam S8 = 4'b1000; //walk_EW
localparam S9 = 4'b1001; //Emergency_EW

always @(*) begin
    NS_Green = 1'b0;
    NS_yellow = 1'b0;
    NS_red = 1'b0;
    EW_Green = 1'b0;
    EW_yellow = 1'b0;
    EW_red = 1'b0;
    walk_NS = 1'b0;
    dont_walk_NS = 1'b0;
    walk_EW = 1'b0;
    dont_walk_EW = 1'b0;

    case(current_state)
        S0 : begin
            NS_Green = 1'b1;
            NS_yellow = 1'b0;
            NS_red = 1'b0;
            EW_Green = 1'b0;
            EW_yellow = 1'b0;
            EW_red = 1'b1;
            walk_NS = 1'b0;
            dont_walk_NS = 1'b1;
            walk_EW = 1'b0;
            dont_walk_EW = 1'b1;
        end

        S1 : begin
            NS_Green = 1'b0;
            NS_yellow = 1'b1;
            NS_red = 1'b0;
            EW_Green = 1'b0;
            EW_yellow = 1'b0;
            EW_red = 1'b1;
            walk_NS = 1'b0;
            dont_walk_NS = 1'b1;
            walk_EW = 1'b0;
            dont_walk_EW = 1'b1;
        end

        S2 : begin
            NS_Green = 1'b0;
            NS_yellow = 1'b0;
            NS_red = 1'b1;
            EW_Green = 1'b0;
            EW_yellow = 1'b0;
            EW_red = 1'b1;
            walk_NS = 1'b0;
            dont_walk_NS = 1'b1;
            walk_EW = 1'b0;
            dont_walk_EW = 1'b1;
        end

        S3 : begin
            NS_Green = 1'b0;
            NS_yellow = 1'b0;
            NS_red = 1'b1;
            EW_Green = 1'b0;
            EW_yellow = 1'b0;
            EW_red = 1'b1;
            walk_NS = 1'b1;
            dont_walk_NS = 1'b0;
            walk_EW = 1'b0;
            dont_walk_EW = 1'b1;
        end

        S4 : begin
            NS_Green = 1'b1;
            NS_yellow = 1'b0;
            NS_red = 1'b0;
            EW_Green = 1'b0;
            EW_yellow = 1'b0;
            EW_red = 1'b1;
            walk_NS = 1'b0;
            dont_walk_NS = 1'b1;
            walk_EW = 1'b0;
            dont_walk_EW = 1'b1;
        end

        S5 : begin
            NS_Green = 1'b0;
            NS_yellow = 1'b0;
            NS_red = 1'b1;
            EW_Green = 1'b1;
            EW_yellow = 1'b0;
            EW_red = 1'b0;
            walk_NS = 1'b0;
            dont_walk_NS = 1'b1;
            walk_EW = 1'b0;
            dont_walk_EW = 1'b1;
        end

        S6 : begin
            NS_Green = 1'b0;
            NS_yellow = 1'b0;
            NS_red = 1'b1;
            EW_Green = 1'b0;
            EW_yellow = 1'b1;
            EW_red = 1'b0;
            walk_NS = 1'b0;
            dont_walk_NS = 1'b1;
            walk_EW = 1'b0;
            dont_walk_EW = 1'b1;
        end

        S7 : begin
            NS_Green = 1'b0;
            NS_yellow = 1'b0;
            NS_red = 1'b1;
            EW_Green = 1'b0;
            EW_yellow = 1'b0;
            EW_red = 1'b1;
            walk_NS = 1'b0;
            dont_walk_NS = 1'b1;
            walk_EW = 1'b0;
            dont_walk_EW = 1'b1;
        end

        S8 : begin
            NS_Green = 1'b0;
            NS_yellow = 1'b0;
            NS_red = 1'b1;
            EW_Green = 1'b0;
            EW_yellow = 1'b0;
            EW_red = 1'b1;
            walk_NS = 1'b0;
            dont_walk_NS = 1'b1;
            walk_EW = 1'b1;
            dont_walk_EW = 1'b0;
        end

        S9 : begin
            NS_Green = 1'b0;
            NS_yellow = 1'b0;
            NS_red = 1'b1;
            EW_Green = 1'b1;
            EW_yellow = 1'b0;
            EW_red = 1'b0;
            walk_NS = 1'b0;
            dont_walk_NS = 1'b1;
            walk_EW = 1'b0;
            dont_walk_EW = 1'b1;
        end

        default : begin
            NS_Green = 1'b0;
            NS_yellow = 1'b0;
            NS_red = 1'b0;
            EW_Green = 1'b0;
            EW_yellow = 1'b0;
            EW_red = 1'b0;
            walk_NS = 1'b0;
            dont_walk_NS = 1'b0;
            walk_EW = 1'b0;
            dont_walk_EW = 1'b0;
        end 
    endcase
end 
endmodule

rtl/next_state_logic.v
`timescale 1ns/1ps

module next_state(
    //input
    input [3:0]current_state,
    input timer_done,
    input emergency_req_NS,
    input emergency_req_EW,
    input ped_req_NS,
    input ped_req_EW,
    //output
    output reg[3:0]next_state
);

//state encoding 

localparam S0 = 4'b0000; // NS_Green
localparam S1 = 4'b0001; // NS_yellow 
localparam S2 = 4'b0010; // All_red_NS
localparam S3 = 4'b0011; // walk_NS
localparam S4 = 4'b0100; //Emergency_NS
localparam S5 = 4'b0101; //EW_Green
localparam S6 = 4'b0110; //EW_yellow
localparam S7 = 4'b0111; //All_red_EW
localparam S8 = 4'b1000; //walk_EW
localparam S9 = 4'b1001; //Emergency_EW

always @(*) begin
    case(current_state)
        S0 : begin
            if(emergency_req_NS) begin
                next_state = S4;
            end 
            else if(emergency_req_EW) begin
                next_state = S9;
            end
            else if(timer_done == 1'b0) begin
                next_state = current_state;
            end 
            else begin
                next_state =  S1;
            end
        end

        S1 : begin
            if(emergency_req_NS) begin
                next_state = S4;
            end 
            else if(emergency_req_EW) begin
                next_state = S9;
            end
            else if(timer_done == 1'b0) begin
                next_state = current_state;
            end 
            else begin
                next_state =  S2;
            end
        end 

        S2 : begin
            if(emergency_req_NS) begin
                next_state = S4;
            end 
            else if(emergency_req_EW) begin
                next_state = S9;
            end
            else if(timer_done == 1'b0) begin
                next_state = current_state;
            end 
            else if(ped_req_NS) begin
                next_state =  S3;
            end
            else begin
                next_state = S5;
            end 
        end

        S3 : begin
            if(emergency_req_NS) begin
                next_state = S4;
            end 
            else if(emergency_req_EW) begin
                next_state = S9;
            end
            else if(timer_done == 1'b0) begin
                next_state = current_state;
            end 
            else begin
                next_state =  S5;
            end
        end

        S4 : begin
            if(emergency_req_NS) begin
                next_state = current_state;
            end 
            else if(timer_done == 1'b0) begin
                next_state = current_state;
            end 
            else begin
                next_state = S0;
            end 
        end 

        S5 : begin
            if(emergency_req_NS) begin
                next_state = S4;
            end 
            else if(emergency_req_EW) begin
                next_state = S9;
            end
            else if(timer_done == 1'b0) begin
                next_state = current_state;
            end 
            else begin
                next_state =  S6;
            end
        end

        S6 : begin
            if(emergency_req_NS) begin
                next_state = S4;
            end 
            else if(emergency_req_EW) begin
                next_state = S9;
            end
            else if(timer_done == 1'b0) begin
                next_state = current_state;
            end 
            else begin
                next_state =  S7;
            end
        end

        S7 : begin
            if(emergency_req_NS) begin
                next_state = S4;
            end 
            else if(emergency_req_EW) begin
                next_state = S9;
            end
            else if(timer_done == 1'b0) begin
                next_state = current_state;
            end 
            else if(ped_req_EW) begin
                next_state =  S8;
            end
            else begin
                next_state = S0;
            end 
        end 

        S8 : begin
            if(emergency_req_NS) begin
                next_state = S4;
            end 
            else if(emergency_req_EW) begin
                next_state = S9;
            end
            else if(timer_done == 1'b0) begin
                next_state = current_state;
            end
            else begin
                next_state = S0;
            end 
        end

        S9 : begin
            if(emergency_req_EW) begin
                next_state = S9;
            end
            else if(timer_done == 1'b0) begin
                next_state = current_state;
            end 
            else begin
                next_state = S0;
            end 
        end 

        default : begin
            next_state = S0;
        end 
    endcase 
end 
endmodule

rtl/state_register.v
`timescale 1ns/1ps 

module state_register(
    input clk,
    input reset,
    input [3:0]next_state,

    //output 
    output reg [3:0]current_state 
);

localparam S0 = 4'b0000;
localparam S1 = 4'b0001;
localparam S2 = 4'b0010;
localparam S3 = 4'b0011;
localparam S4 = 4'b0100;
localparam S5 = 4'b0101;
localparam S6 = 4'b0110;
localparam S7 = 4'b0111;
localparam S8 = 4'b1000;
localparam S9 = 4'b1001;

always @(posedge clk) begin
    if(reset) begin
        current_state <= S0;
    end
    else begin
        current_state <= next_state;
    end
end 
endmodule

rtl/timer.v
`timescale 1ns/1ps 

module timer(
    //INPUT
    input clk,
    input reset,
    input timer_clear,
    input [4:0]target_count,
    
    //OUTPUT
    output timer_done,
);
reg [4:0]count; 

always @(posedge clk) begin
    if (reset) begin
        count <= 5'd0;
    end 
    else if (timer_clear) begin
        count <= 5'd0;
    end 
    else if (count < target_count) begin
        count <= count + 5'd1; 
    end 
    //else begin
    //    count = target_count;
    //end 
end 
assign timer_done = (count >= target_count);
endmodule

rtl/traffic_light_controller.v
`timescale 1ns/1ps

module traffic_light_controller(
    //input 
    input clk,
    input reset,
    input emergency_req_NS,
    input emergency_req_EW,
    input ped_req_NS,
    input ped_req_EW,

    //output
    output NS_green,
    output NS_yellow,
    output NS_red,

    output EW_green,
    output EW_yellow,
    output EW_red,

    output walk_NS,
    output dont_walk_NS,

    output walk_EW,
    output dont_walk_EW
);

//internal connections 

reg [4:0]target_count;

wire timer_clear;
wire timer_done;
wire [3:0]current_state;
wire [3:0]next_state;

//unit 1 

timer u1(
    
    .clk(clk),
    .reset(reset),
    .timer_clear(timer_clear),
    .target_count(target_count),
    
    .timer_done(timer_done)
);

// unit 2 state register 

state_register u2(
    .clk(clk),
    .reset(reset),
    .next_state(next_state),
    
    .current_state(current_state) 
);

//unit 3 next_state 

next_state u3(
    .current_state(current_state),
    .timer_done(timer_done),
    .emergency_req_NS(emergency_req_NS),
    .emergency_req_EW(emergency_req_EW),
    .ped_req_NS(ped_req_NS),
    .ped_req_EW(ped_req_EW),
    
    .next_state(next_state)
);

//unit 4 output logic

output_logic u4(

    .current_state(current_state),
 
    .NS_Green(NS_green),
    .NS_yellow(NS_yellow),
    .NS_red(NS_red),
    .EW_Green(EW_green),
    .EW_yellow(EW_yellow),
    .EW_red(EW_red),
    .walk_NS(walk_NS),
    .dont_walk_NS(dont_walk_NS),
    .walk_EW(walk_EW),
    .dont_walk_EW(dont_walk_EW)
);


//state encoding 

localparam S0 = 4'b0000; // NS_Green
localparam S1 = 4'b0001; // NS_yellow 
localparam S2 = 4'b0010; // All_red_NS
localparam S3 = 4'b0011; // walk_NS
localparam S4 = 4'b0100; //Emergency_NS
localparam S5 = 4'b0101; //EW_Green
localparam S6 = 4'b0110; //EW_yellow
localparam S7 = 4'b0111; //All_red_EW
localparam S8 = 4'b1000; //walk_EW
localparam S9 = 4'b1001; //Emergency_EW


always @(*) begin
    case(current_state)
        S0 : target_count = 5'd30;
        S1 : target_count = 5'd5;
        S2 : target_count = 5'd2;
        S3 : target_count = 5'd8;
        S4 : target_count = 5'd10;   
        S5 : target_count = 5'd30; 
        S6 : target_count = 5'd5;
        S7 : target_count = 5'd2;
        S8 : target_count = 5'd8;
        S9 : target_count = 5'd10;
        default : target_count = 5'd0;
    endcase
end 

assign timer_clear = (current_state != next_state);

endmodule

tb/traffic_light_controller_TB.v
`timescale 1ns/1ps

module traffic_light_controller_tb ;

reg clk;
reg reset;
reg emergency_req_NS;
reg emergency_req_EW;
reg ped_req_NS;
reg ped_req_EW;

wire NS_green;
wire NS_yellow;
wire NS_red;

wire EW_green;
wire EW_yellow;
wire EW_red;

wire walk_NS;
wire dont_walk_NS;

wire walk_EW;
wire dont_walk_EW;

//state encoding 

localparam S0 = 4'b0000; // NS_Green
localparam S1 = 4'b0001; // NS_yellow 
localparam S2 = 4'b0010; // All_red_NS
localparam S3 = 4'b0011; // walk_NS
localparam S4 = 4'b0100; //Emergency_NS
localparam S5 = 4'b0101; //EW_Green
localparam S6 = 4'b0110; //EW_yellow
localparam S7 = 4'b0111; //All_red_EW
localparam S8 = 4'b1000; //walk_EW
localparam S9 = 4'b1001; //Emergency_EW

traffic_light_controller dut(
    .clk(clk),
    .reset(reset),
    .emergency_req_NS(emergency_req_NS),
    .emergency_req_EW(emergency_req_EW),
    .ped_req_NS(ped_req_NS),
    .ped_req_EW(ped_req_EW),

    .NS_green(NS_green),
    .NS_yellow(NS_yellow),
    .NS_red(NS_red),

    .EW_green(EW_green),
    .EW_yellow(EW_yellow),
    .EW_red(EW_red),

    .walk_NS(walk_NS),
    .dont_walk_NS(dont_walk_NS),

    .walk_EW(walk_EW),
    .dont_walk_EW(dont_walk_EW)
);

initial begin 
    clk = 1'b0;
end

always #5 clk = ~ clk;

initial begin 
    $dumpfile("wave/traffic_light_controller.vcd");
    $dumpvars(0, traffic_light_controller_tb);
end 

initial begin
    @(posedge clk);

    //case 1 : when reset = 1  
    reset = 1'b1;
    emergency_req_NS = 1'b0;
    emergency_req_EW = 1'b0;
    ped_req_NS = 1'b0;
    ped_req_EW = 1'b0;
    @(posedge clk);
    
    @(negedge clk);
    reset = 1'b0;
    #1;

    //case 2 checking normal condition of the signal
    reset = 1'b0;
    emergency_req_NS = 1'b0;
    emergency_req_EW = 1'b0;
    ped_req_NS = 1'b0;
    ped_req_EW = 1'b0;
    repeat(74) @(posedge clk);


   // case 3 : checking pedestrian request

    reset = 1'b0;
    emergency_req_NS = 1'b0;
    emergency_req_EW = 1'b0;
    ped_req_NS = 1'b0;
    ped_req_EW = 1'b0;

    while(dut.current_state != S2) begin
        @(posedge clk);
        #1;
    end
    while(dut.timer_done != 1)begin
        @(posedge clk);
        #1;
    end

    @(negedge clk);
    ped_req_NS = 1'b1;
    #1;
    @(posedge clk);
    #1;
    while(dut.current_state != S7) begin
        @(posedge clk);
        #1;
    end
    while(dut.timer_done != 1) begin
        @(posedge clk);
        #1;
    end

    @(negedge clk);
    ped_req_EW = 1'b1;
    #1;
    @(posedge clk);
    #1;
    if(dut.current_state == S8)
        $display(" case 3 PASS");
    else
        $display(" case 3 FAIL");

    //case 4 : ped_req_EW comes when system is in S1 state it should change state after S7 only

    reset = 1'b0;
    emergency_req_NS = 1'b0;
    emergency_req_EW = 1'b0;
    ped_req_NS = 1'b0;
    ped_req_EW = 1'b0;
 
    while(dut.current_state != S1) begin
        @(posedge clk);
        #1;
    end
    while(dut.timer_done != 1) begin
        @(posedge clk);
        #1;
    end
    @(negedge clk);
    ped_req_EW =1'b1;
    #1;
    @(posedge clk);
    #1;

    if(dut.current_state == S2)
        $display("all good");
    else
        $display("problem after S1");

    while(dut.current_state != S0)begin
        @(posedge clk)
        #1;
    end
    while(dut.timer_done != 1) begin
        @(posedge clk);
        #1;
    end;
    @(negedge clk);
    ped_req_EW = 1'b0;
    #1;
    if(dut.current_state == S0)
        $display("case 4 PASS");
    else
        $display("case 4 FAIL");

    //case 5 : current state is S5 and emergency_req_NS = 1

    while(dut.current_state != S5) begin
        @(posedge clk);
        #1;
    end 
    while(dut.timer_done != 1) begin
        @(posedge clk);
        #1;
    end
    @(negedge clk);
    emergency_req_NS = 1'b1;
    #1;
    while(dut.current_state != S4) begin
        @(posedge clk);
        #1;
    end 
    @(negedge clk);
    emergency_req_NS = 1'b0;
    #1;
    while(dut.current_state != S0) begin
        @(posedge clk);
        #1;
    end;
    while(dut.timer_done != 1) begin
        @(posedge clk);
        #1;
    end 
    if(dut.current_state == S0)
        $display("case 5 pass");
    else
        $display("case 5 failed");
    @(posedge clk);

    //case 6 : current state is S6 and emergency_req_EW = 1

    while(dut.current_state != S6) begin
        @(posedge clk);
        #1;
    end 
    while(dut.timer_done != 1) begin
        @(posedge clk);
        #1;
    end
    @(negedge clk);
    emergency_req_EW = 1'b1;
    #1;
    while(dut.current_state != S9) begin
        @(posedge clk);
        #1;
    end 
    @(negedge clk);
    emergency_req_EW = 1'b0;
    #1;
    while(dut.current_state != S0) begin
        @(posedge clk);
        #1;
    end;
    while(dut.timer_done != 1) begin
        @(posedge clk);
        #1;
    end 
    if(dut.current_state == S0)
        $display("case 6 pass");
    else
        $display("case 6 failed");

    $finish;
end 
endmodule

wave/traffic_light_controller.vcd
$date
	Wed Aug 12 23:23:06 2026
$end
$version
	Icarus Verilog
$end
$timescale
	1ps
$end
$scope module traffic_light_controller_tb $end
$var wire 1 ! walk_NS $end
$var wire 1 " walk_EW $end
$var wire 1 # dont_walk_NS $end
$var wire 1 $ dont_walk_EW $end
$var wire 1 % NS_yellow $end
$var wire 1 & NS_red $end
$var wire 1 ' NS_green $end
$var wire 1 ( EW_yellow $end
$var wire 1 ) EW_red $end
$var wire 1 * EW_green $end
$var parameter 4 + S0 $end
$var parameter 4 , S1 $end
$var parameter 4 - S2 $end
$var parameter 4 . S3 $end
$var parameter 4 / S4 $end
$var parameter 4 0 S5 $end
$var parameter 4 1 S6 $end
$var parameter 4 2 S7 $end
$var parameter 4 3 S8 $end
$var parameter 4 4 S9 $end
$var reg 1 5 clk $end
$var reg 1 6 emergency_req_EW $end
$var reg 1 7 emergency_req_NS $end
$var reg 1 8 ped_req_EW $end
$var reg 1 9 ped_req_NS $end
$var reg 1 : reset $end
$scope module dut $end
$var wire 1 5 clk $end
$var wire 1 6 emergency_req_EW $end
$var wire 1 7 emergency_req_NS $end
$var wire 1 8 ped_req_EW $end
$var wire 1 9 ped_req_NS $end
$var wire 1 : reset $end
$var wire 1 ! walk_NS $end
$var wire 1 " walk_EW $end
$var wire 1 ; timer_done $end
$var wire 1 < timer_clear $end
$var wire 4 = next_state [3:0] $end
$var wire 1 # dont_walk_NS $end
$var wire 1 $ dont_walk_EW $end
$var wire 4 > current_state [3:0] $end
$var wire 1 % NS_yellow $end
$var wire 1 & NS_red $end
$var wire 1 ' NS_green $end
$var wire 1 ( EW_yellow $end
$var wire 1 ) EW_red $end
$var wire 1 * EW_green $end
$var parameter 4 ? S0 $end
$var parameter 4 @ S1 $end
$var parameter 4 A S2 $end
$var parameter 4 B S3 $end
$var parameter 4 C S4 $end
$var parameter 4 D S5 $end
$var parameter 4 E S6 $end
$var parameter 4 F S7 $end
$var parameter 4 G S8 $end
$var parameter 4 H S9 $end
$var reg 5 I target_count [4:0] $end
$scope module u1 $end
$var wire 1 5 clk $end
$var wire 1 : reset $end
$var wire 5 J target_count [4:0] $end
$var wire 1 < timer_clear $end
$var wire 1 ; timer_done $end
$var reg 5 K count [4:0] $end
$upscope $end
$scope module u2 $end
$var wire 1 5 clk $end
$var wire 1 : reset $end
$var wire 4 L next_state [3:0] $end
$var parameter 4 M S0 $end
$var parameter 4 N S1 $end
$var parameter 4 O S2 $end
$var parameter 4 P S3 $end
$var parameter 4 Q S4 $end
$var parameter 4 R S5 $end
$var parameter 4 S S6 $end
$var parameter 4 T S7 $end
$var parameter 4 U S8 $end
$var parameter 4 V S9 $end
$var reg 4 W current_state [3:0] $end
$upscope $end
$scope module u3 $end
$var wire 4 X current_state [3:0] $end
$var wire 1 6 emergency_req_EW $end
$var wire 1 7 emergency_req_NS $end
$var wire 1 8 ped_req_EW $end
$var wire 1 9 ped_req_NS $end
$var wire 1 ; timer_done $end
$var parameter 4 Y S0 $end
$var parameter 4 Z S1 $end
$var parameter 4 [ S2 $end
$var parameter 4 \ S3 $end
$var parameter 4 ] S4 $end
$var parameter 4 ^ S5 $end
$var parameter 4 _ S6 $end
$var parameter 4 ` S7 $end
$var parameter 4 a S8 $end
$var parameter 4 b S9 $end
$var reg 4 c next_state [3:0] $end
$upscope $end
$scope module u4 $end
$var wire 4 d current_state [3:0] $end
$var parameter 4 e S0 $end
$var parameter 4 f S1 $end
$var parameter 4 g S2 $end
$var parameter 4 h S3 $end
$var parameter 4 i S4 $end
$var parameter 4 j S5 $end
$var parameter 4 k S6 $end
$var parameter 4 l S7 $end
$var parameter 4 m S8 $end
$var parameter 4 n S9 $end
$var reg 1 * EW_Green $end
$var reg 1 ) EW_red $end
$var reg 1 ( EW_yellow $end
$var reg 1 ' NS_Green $end
$var reg 1 & NS_red $end
$var reg 1 % NS_yellow $end
$var reg 1 $ dont_walk_EW $end
$var reg 1 # dont_walk_NS $end
$var reg 1 " walk_EW $end
$var reg 1 ! walk_NS $end
$upscope $end
$upscope $end
$upscope $end
$enddefinitions $end
$comment Show the parameter values. $end
$dumpall
b1001 n
b1000 m
b111 l
b110 k
b101 j
b100 i
b11 h
b10 g
b1 f
b0 e
b1001 b
b1000 a
b111 `
b110 _
b101 ^
b100 ]
b11 \
b10 [
b1 Z
b0 Y
b1001 V
b1000 U
b111 T
b110 S
b101 R
b100 Q
b11 P
b10 O
b1 N
b0 M
b1001 H
b1000 G
b111 F
b110 E
b101 D
b100 C
b11 B
b10 A
b1 @
b0 ?
b1001 4
b1000 3
b111 2
b110 1
b101 0
b100 /
b11 .
b10 -
b1 ,
b0 +
$end
#0
$dumpvars
bx d
bx c
bx X
bx W
bx L
bx K
bx J
bx I
bx >
bx =
x<
x;
x:
x9
x8
x7
x6
05
x*
x)
x(
x'
x&
x%
x$
x#
x"
x!
$end
#5000
0;
b11110 I
b11110 J
1$
0"
1#
0!
1)
0(
0*
0&
0%
1'
b0 K
0<
b0 >
b0 W
b0 X
b0 d
b0 =
b0 L
b0 c
08
09
06
07
1:
15
#10000
05
#15000
15
#20000
0:
05
#25000
b1 K
15
#30000
05
#35000
b10 K
15
#40000
05
#45000
b11 K
15
#50000
05
#55000
b100 K
15
#60000
05
#65000
b101 K
15
#70000
05
#75000
b110 K
15
#80000
05
#85000
b111 K
15
#90000
05
#95000
b1000 K
15
#100000
05
#105000
b1001 K
15
#110000
05
#115000
b1010 K
15
#120000
05
#125000
b1011 K
15
#130000
05
#135000
b1100 K
15
#140000
05
#145000
b1101 K
15
#150000
05
#155000
b1110 K
15
#160000
05
#165000
b1111 K
15
#170000
05
#175000
b10000 K
15
#180000
05
#185000
b10001 K
15
#190000
05
#195000
b10010 K
15
#200000
05
#205000
b10011 K
15
#210000
05
#215000
b10100 K
15
#220000
05
#225000
b10101 K
15
#230000
05
#235000
b10110 K
15
#240000
05
#245000
b10111 K
15
#250000
05
#255000
b11000 K
15
#260000
05
#265000
b11001 K
15
#270000
05
#275000
b11010 K
15
#280000
05
#285000
b11011 K
15
#290000
05
#295000
b11100 K
15
#300000
05
#305000
b11101 K
15
#310000
05
#315000
1<
b1 =
b1 L
b1 c
1;
b11110 K
15
#320000
05
#325000
1%
1$
1#
1)
0'
b101 I
b101 J
0;
b0 K
0<
b1 >
b1 W
b1 X
b1 d
15
#330000
05
#335000
b1 K
15
#340000
05
#345000
b10 K
15
#350000
05
#355000
b11 K
15
#360000
05
#365000
b100 K
15
#370000
05
#375000
1<
b10 =
b10 L
b10 c
1;
b101 K
15
#380000
05
#385000
b10 I
b10 J
1&
1$
1#
1)
0%
0;
b0 K
0<
b10 >
b10 W
b10 X
b10 d
15
#390000
05
#395000
b1 K
15
#400000
05
#405000
1<
b101 =
b101 L
b101 c
1;
b10 K
15
#410000
05
#415000
1*
1$
1#
0)
1&
b11110 I
b11110 J
0<
b101 >
b101 W
b101 X
b101 d
0;
b0 K
15
#420000
05
#425000
b1 K
15
#430000
05
#435000
b10 K
15
#440000
05
#445000
b11 K
15
#450000
05
#455000
b100 K
15
#460000
05
#465000
b101 K
15
#470000
05
#475000
b110 K
15
#480000
05
#485000
b111 K
15
#490000
05
#495000
b1000 K
15
#500000
05
#505000
b1001 K
15
#510000
05
#515000
b1010 K
15
#520000
05
#525000
b1011 K
15
#530000
05
#535000
b1100 K
15
#540000
05
#545000
b1101 K
15
#550000
05
#555000
b1110 K
15
#560000
05
#565000
b1111 K
15
#570000
05
#575000
b10000 K
15
#580000
05
#585000
b10001 K
15
#590000
05
#595000
b10010 K
15
#600000
05
#605000
b10011 K
15
#610000
05
#615000
b10100 K
15
#620000
05
#625000
b10101 K
15
#630000
05
#635000
b10110 K
15
#640000
05
#645000
b10111 K
15
#650000
05
#655000
b11000 K
15
#660000
05
#665000
b11001 K
15
#670000
05
#675000
b11010 K
15
#680000
05
#685000
b11011 K
15
#690000
05
#695000
b11100 K
15
#700000
05
#705000
b11101 K
15
#710000
05
#715000
1<
b110 =
b110 L
b110 c
1;
b11110 K
15
#720000
05
#725000
b101 I
b101 J
1(
1$
1#
0*
1&
0;
b0 K
0<
b110 >
b110 W
b110 X
b110 d
15
#730000
05
#735000
b1 K
15
#740000
05
#745000
b10 K
15
#750000
05
#755000
b11 K
15
#760000
05
#765000
b100 K
15
#770000
05
#775000
1<
b111 =
b111 L
b111 c
1;
b101 K
15
#780000
05
#785000
1)
1$
1#
0(
1&
b10 I
b10 J
0;
b0 K
0<
b111 >
b111 W
b111 X
b111 d
15
#790000
05
#795000
b1 K
15
#800000
05
#805000
1<
b0 =
b0 L
b0 c
1;
b10 K
15
#810000
05
#815000
b11110 I
b11110 J
1'
1$
1#
1)
0&
0<
b0 >
b0 W
b0 X
b0 d
0;
b0 K
15
#820000
05
#825000
b1 K
15
#830000
05
#835000
b10 K
15
#840000
05
#845000
b11 K
15
#850000
05
#855000
b100 K
15
#860000
05
#865000
b101 K
15
#870000
05
#875000
b110 K
15
#880000
05
#885000
b111 K
15
#890000
05
#895000
b1000 K
15
#900000
05
#905000
b1001 K
15
#910000
05
#915000
b1010 K
15
#920000
05
#925000
b1011 K
15
#930000
05
#935000
b1100 K
15
#940000
05
#945000
b1101 K
15
#950000
05
#955000
b1110 K
15
#960000
05
#965000
b1111 K
15
#970000
05
#975000
b10000 K
15
#980000
05
#985000
b10001 K
15
#990000
05
#995000
b10010 K
15
#1000000
05
#1005000
b10011 K
15
#1010000
05
#1015000
b10100 K
15
#1020000
05
#1025000
b10101 K
15
#1030000
05
#1035000
b10110 K
15
#1040000
05
#1045000
b10111 K
15
#1050000
05
#1055000
b11000 K
15
#1060000
05
#1065000
b11001 K
15
#1070000
05
#1075000
b11010 K
15
#1080000
05
#1085000
b11011 K
15
#1090000
05
#1095000
b11100 K
15
#1100000
05
#1105000
b11101 K
15
#1110000
05
#1115000
1<
b1 =
b1 L
b1 c
1;
b11110 K
15
#1120000
05
#1125000
1%
1$
1#
1)
0'
b101 I
b101 J
0;
b0 K
0<
b1 >
b1 W
b1 X
b1 d
15
#1130000
05
#1135000
b1 K
15
#1140000
05
#1145000
b10 K
15
#1150000
05
#1155000
b11 K
15
#1160000
05
#1165000
b100 K
15
#1170000
05
#1175000
1<
b10 =
b10 L
b10 c
1;
b101 K
15
#1180000
05
#1185000
b10 I
b10 J
1&
1$
1#
1)
0%
0;
b0 K
0<
b10 >
b10 W
b10 X
b10 d
15
#1190000
05
#1195000
b1 K
15
#1200000
05
#1205000
1<
b101 =
b101 L
b101 c
1;
b10 K
15
#1210000
b11 =
b11 L
b11 c
19
05
#1215000
1!
1$
0#
1)
1&
b1000 I
b1000 J
0<
b11 >
b11 W
b11 X
b11 d
0;
b0 K
15
#1220000
05
#1225000
b1 K
15
#1230000
05
#1235000
b10 K
15
#1240000
05
#1245000
b11 K
15
#1250000
05
#1255000
b100 K
15
#1260000
05
#1265000
b101 K
15
#1270000
05
#1275000
b110 K
15
#1280000
05
#1285000
b111 K
15
#1290000
05
#1295000
1<
b101 =
b101 L
b101 c
1;
b1000 K
15
#1300000
05
#1305000
b11110 I
b11110 J
1#
1*
1$
0!
0)
1&
0;
b0 K
0<
b101 >
b101 W
b101 X
b101 d
15
#1310000
05
#1315000
b1 K
15
#1320000
05
#1325000
b10 K
15
#1330000
05
#1335000
b11 K
15
#1340000
05
#1345000
b100 K
15
#1350000
05
#1355000
b101 K
15
#1360000
05
#1365000
b110 K
15
#1370000
05
#1375000
b111 K
15
#1380000
05
#1385000
b1000 K
15
#1390000
05
#1395000
b1001 K
15
#1400000
05
#1405000
b1010 K
15
#1410000
05
#1415000
b1011 K
15
#1420000
05
#1425000
b1100 K
15
#1430000
05
#1435000
b1101 K
15
#1440000
05
#1445000
b1110 K
15
#1450000
05
#1455000
b1111 K
15
#1460000
05
#1465000
b10000 K
15
#1470000
05
#1475000
b10001 K
15
#1480000
05
#1485000
b10010 K
15
#1490000
05
#1495000
b10011 K
15
#1500000
05
#1505000
b10100 K
15
#1510000
05
#1515000
b10101 K
15
#1520000
05
#1525000
b10110 K
15
#1530000
05
#1535000
b10111 K
15
#1540000
05
#1545000
b11000 K
15
#1550000
05
#1555000
b11001 K
15
#1560000
05
#1565000
b11010 K
15
#1570000
05
#1575000
b11011 K
15
#1580000
05
#1585000
b11100 K
15
#1590000
05
#1595000
b11101 K
15
#1600000
05
#1605000
1<
b110 =
b110 L
b110 c
1;
b11110 K
15
#1610000
05
#1615000
1(
1$
1#
0*
1&
b101 I
b101 J
0<
b110 >
b110 W
b110 X
b110 d
0;
b0 K
15
#1620000
05
#1625000
b1 K
15
#1630000
05
#1635000
b10 K
15
#1640000
05
#1645000
b11 K
15
#1650000
05
#1655000
b100 K
15
#1660000
05
#1665000
1<
b111 =
b111 L
b111 c
1;
b101 K
15
#1670000
05
#1675000
b10 I
b10 J
1)
1$
1#
0(
1&
0<
b111 >
b111 W
b111 X
b111 d
0;
b0 K
15
#1680000
05
#1685000
b1 K
15
#1690000
05
#1695000
1<
b0 =
b0 L
b0 c
1;
b10 K
15
#1700000
b1000 =
b1000 L
b1000 c
18
05
#1705000
1"
0$
1#
1)
1&
b1000 I
b1000 J
0;
b0 K
0<
b1000 >
b1000 W
b1000 X
b1000 d
15
#1706000
08
09
#1710000
05
#1715000
b1 K
15
#1720000
05
#1725000
b10 K
15
#1730000
05
#1735000
b11 K
15
#1740000
05
#1745000
b100 K
15
#1750000
05
#1755000
b101 K
15
#1760000
05
#1765000
b110 K
15
#1770000
05
#1775000
b111 K
15
#1780000
05
#1785000
1<
b0 =
b0 L
b0 c
1;
b1000 K
15
#1790000
05
#1795000
b11110 I
b11110 J
1$
1'
0"
1#
1)
0&
0<
b0 >
b0 W
b0 X
b0 d
0;
b0 K
15
#1800000
05
#1805000
b1 K
15
#1810000
05
